ghorse/__init__.py
ghorse/_functional.py
ghorse/_ghorse.cp312-win_amd64.pyd
ghorse/_ghorse/include/ghorse/freeze.h
ghorse/_ghorse/include/ghorse/graph.h
ghorse/_ghorse/src/freeze.c
ghorse/_ghorse/src/graph.c
ghorse/_ghorse/src/module.c
ghorse-0.0.0.dist-info/METADATA
ghorse-0.0.0.dist-info/WHEEL
ghorse-0.0.0.dist-info/top_level.txt
ghorse-0.0.0.dist-info/RECORD
